git_secret_scanner/__init__.py
git_secret_scanner/__main__.py
git_secret_scanner/cli.py
git_secret_scanner/console.py
git_secret_scanner/constants.py
git_secret_scanner/scan.py
git_secret_scanner/report/__init__.py
git_secret_scanner/report/report.py
git_secret_scanner/report/secret_kind.py
git_secret_scanner/scanners/__init__.py
git_secret_scanner/scanners/base.py
git_secret_scanner/scanners/gitleaks/__init__.py
git_secret_scanner/scanners/gitleaks/mapping.py
git_secret_scanner/scanners/gitleaks/scanner.py
git_secret_scanner/scanners/trufflehog/__init__.py
git_secret_scanner/scanners/trufflehog/mapping.py
git_secret_scanner/scanners/trufflehog/scanner.py
git_secret_scanner/scm/__init__.py
git_secret_scanner/scm/git.py
git_secret_scanner/scm/github.py
git_secret_scanner/scm/gitlab.py
git_secret_scanner-0.4.0.dist-info/METADATA
git_secret_scanner-0.4.0.dist-info/WHEEL
git_secret_scanner-0.4.0.dist-info/entry_points.txt
git_secret_scanner-0.4.0.dist-info/licenses/LICENSE
git_secret_scanner-0.4.0.dist-info/RECORD
