Metadata-Version: 2.1
Name: git-secret-scanner
Version: 0.4.0
Summary: Find secrets in git repositories with TruffleHog & Gitleaks
Project-URL: Homepage, https://github.com/padok-team/git-secret-scanner
Project-URL: Repository, https://github.com/padok-team/git-secret-scanner
Author: Padok
License-Expression: Apache-2.0
License-File: LICENSE
Keywords: git,scan,secret,security
Classifier: Intended Audience :: Developers
Classifier: Intended Audience :: System Administrators
Classifier: License :: OSI Approved :: Apache Software License
Classifier: Operating System :: MacOS
Classifier: Operating System :: POSIX :: Linux
Classifier: Programming Language :: Python :: 3
Classifier: Programming Language :: Python :: 3.11
Requires-Python: >=3.11
Requires-Dist: pygithub==1.59.1
Requires-Dist: python-gitlab==3.15.0
Requires-Dist: rich==13.5.3
Requires-Dist: typer==0.9.0
